django_dans_waitlist/__init__.py
django_dans_waitlist/admin.py
django_dans_waitlist/apps.py
django_dans_waitlist/models.py
django_dans_waitlist/permissions.py
django_dans_waitlist/py.typed
django_dans_waitlist/regex.py
django_dans_waitlist/urls.py
django_dans_waitlist/views.py
django_dans_waitlist/migrations/0001_initial.py
django_dans_waitlist/migrations/__init__.py
django_dans_waitlist/serializers/__init__.py
django_dans_waitlist/serializers/waitlist.py
django_dans_waitlist/templates/emails/base.html
django_dans_waitlist/templates/emails/waitlist-email.html
django_dans_waitlist/templates/emails/widgets/signature.html
django_dans_waitlist/test/__init__.py
django_dans_waitlist/test/settings.py
django_dans_waitlist/test/model_tests/__init__.py
django_dans_waitlist/test/model_tests/base.py
django_dans_waitlist/test/model_tests/waitlist/__init__.py
django_dans_waitlist/test/model_tests/waitlist/test_waitlist_entry.py
django_dans_waitlist/test/view_tests/__init__.py
django_dans_waitlist/test/view_tests/base.py
django_dans_waitlist/test/view_tests/waitlist_view_tests/__init__.py
django_dans_waitlist/test/view_tests/waitlist_view_tests/test_waitlist_entry_emails_view_set.py
django_dans_waitlist/test/view_tests/waitlist_view_tests/test_waitlist_entry_view_set.py
django_dans_waitlist-1.0.3.dist-info/AUTHORS
django_dans_waitlist-1.0.3.dist-info/LICENSE
django_dans_waitlist-1.0.3.dist-info/METADATA
django_dans_waitlist-1.0.3.dist-info/WHEEL
django_dans_waitlist-1.0.3.dist-info/top_level.txt
django_dans_waitlist-1.0.3.dist-info/RECORD
